gptty/__init__.py
gptty/__main__.py
gptty/config.py
gptty/context.py
gptty/gptty.py
gptty/tagging.py
gptty-0.2.7.dist-info/LICENSE
gptty-0.2.7.dist-info/METADATA
gptty-0.2.7.dist-info/WHEEL
gptty-0.2.7.dist-info/entry_points.txt
gptty-0.2.7.dist-info/top_level.txt
gptty-0.2.7.dist-info/RECORD
