Metadata-Version: 2.1
Name: gptty
Version: 0.2.7
Summary: Chat GPT wrapper in your TTY 
Home-page: https://github.com/signebedi/gptty
Author: Sig Janoska-Bedi
Author-email: signe@atreeus.com
Classifier: Programming Language :: Python :: 3
Classifier: License :: OSI Approved :: MIT License
Classifier: Operating System :: OS Independent
Requires-Python: >=3.8
License-File: LICENSE
Requires-Dist: aioconsole (<0.7.0)
Requires-Dist: click (<9.0.0)
Requires-Dist: nltk (<4.0.0)
Requires-Dist: openai (==0.27.2)
Requires-Dist: pandas (<2.0.0)
Requires-Dist: prompt-toolkit (<4.0.0)
Requires-Dist: textblob (<1.0.0)
Requires-Dist: tiktoken (<1.0.0)
